grapa/GUI.py
grapa/__init__.py
grapa/_curve_OLD_until2025March.py
grapa/colorscale.py
grapa/config.txt
grapa/config_anch.txt
grapa/config_default.txt
grapa/constants.py
grapa/curve.py
grapa/curve_image.py
grapa/curve_inset.py
grapa/curve_subplot.py
grapa/database.py
grapa/grapalog.log
grapa/graph.py
grapa/keywordsdata_curve.txt
grapa/keywordsdata_graph.txt
grapa/keywordsdata_headers.txt
grapa/mathModule.py
grapa/version_notes.rst
grapa/datatypes/AM0_2000_ASTM_E-490-00.txt
grapa/datatypes/AM1-5_Ed2-2008.txt
grapa/datatypes/EQE_20.4_cell.txt
grapa/datatypes/EQE_ShockleyQueisser.txt
grapa/datatypes/EQE_absorption_CdS.txt
grapa/datatypes/EQE_referenceSpectra.txt
grapa/datatypes/MCA_default.txt
grapa/datatypes/XML_dataformats.txt
grapa/datatypes/XRD_fitparameters.txt
grapa/datatypes/XRF_fitparameters.txt
grapa/datatypes/XRF_photonenergiesintensities.txt
grapa/datatypes/__init__.py
grapa/datatypes/curveArrhenius.py
grapa/datatypes/curveCV.py
grapa/datatypes/curveCf.py
grapa/datatypes/curveEQE.py
grapa/datatypes/curveJV.py
grapa/datatypes/curveJscVoc.py
grapa/datatypes/curveMCA.py
grapa/datatypes/curveMath.py
grapa/datatypes/curveSIMS.py
grapa/datatypes/curveSpectrum.py
grapa/datatypes/curveTRPL.py
grapa/datatypes/curveXRD.py
grapa/datatypes/graphCV.py
grapa/datatypes/graphCf.py
grapa/datatypes/graphEQE.py
grapa/datatypes/graphEQE_CSU.py
grapa/datatypes/graphJV.py
grapa/datatypes/graphJVDarkIllum.py
grapa/datatypes/graphJV_Ossila.py
grapa/datatypes/graphJV_Wavelabs.py
grapa/datatypes/graphMBE_TinyTusker.py
grapa/datatypes/graphMBElog.py
grapa/datatypes/graphMCA.py
grapa/datatypes/graphMCAfit.py
grapa/datatypes/graphPAIOS.py
grapa/datatypes/graphPGZ.py
grapa/datatypes/graphPLQY.py
grapa/datatypes/graphSIMS.py
grapa/datatypes/graphSPE.py
grapa/datatypes/graphScaps.py
grapa/datatypes/graphSpectrum.py
grapa/datatypes/graphSquidAdmiral.py
grapa/datatypes/graphTRPL.py
grapa/datatypes/graphXLS.py
grapa/datatypes/graphXML.py
grapa/datatypes/graphXPS.py
grapa-0.7.0.0.dist-info/licenses/LICENSE
grapa-0.7.0.0.dist-info/METADATA
grapa-0.7.0.0.dist-info/WHEEL
grapa-0.7.0.0.dist-info/top_level.txt
grapa-0.7.0.0.dist-info/RECORD
